glcli/cli.py
glcli/environment.py
greenlight_cli-0.2.0.dist-info/METADATA
greenlight_cli-0.2.0.dist-info/WHEEL
greenlight_cli-0.2.0.dist-info/entry_points.txt
greenlight_cli-0.2.0.dist-info/RECORD
